mest/__init__.py
mest/__main__.py
mest/version.py
mest/app/__init__.py
mest/app/_state.py
mest/app/mest_app.py
mest/app/mest_conf.py
mest/app/_logs/__init__.py
mest/app/_logs/enrichment.py
mest/app/_logs/initializers.py
mest/app/_logs/formatters/__init__.py
mest/app/_logs/formatters/dict.py
mest/app/_logs/formatters/json.py
mest/app/_middlewares/__init__.py
mest/app/_middlewares/response_time.py
mest/app/api/__init__.py
mest/app/api/_request_parser.py
mest/app/api/_router.py
mest/cli/__init__.py
mest/cli/_common.py
mest/cli/run.py
mest/cli/shell.py
mest/cli/test.py
mest/models/__init__.py
mest/models/_base.py
mest/utils/__init__.py
mest/utils/_singleton.py
mest/utils/monitor.py
mest-0.1.0a0.data/data/README.md
tests/__init__.py
tests/common.py
tests/test_app.py
tests/test_model.py
tests/test_router.py
tests/test_utils.py
mest-0.1.0a0.dist-info/LICENSE.md
mest-0.1.0a0.dist-info/METADATA
mest-0.1.0a0.dist-info/WHEEL
mest-0.1.0a0.dist-info/entry_points.txt
mest-0.1.0a0.dist-info/top_level.txt
mest-0.1.0a0.dist-info/RECORD
